avogadro/__init__.py
avogadro/__version__.py
avogadro/agent.py
avogadro/cpu_agent.py
avogadro/disk_agent.py
avogadro/export.py
avogadro/grok_forwarder.py
avogadro/keylog_agent.py
avogadro/keys.py
avogadro/memory_agent.py
avogadro/model_params.py
avogadro/network_agent.py
avogadro/nupic_forwarder.py
avogadro/rrdtool.py
numenta_rogue-1.0.1.dist-info/DESCRIPTION.rst
numenta_rogue-1.0.1.dist-info/entry_points.txt
numenta_rogue-1.0.1.dist-info/METADATA
numenta_rogue-1.0.1.dist-info/metadata.json
numenta_rogue-1.0.1.dist-info/RECORD
numenta_rogue-1.0.1.dist-info/top_level.txt
numenta_rogue-1.0.1.dist-info/WHEEL
tools/__init__.py
tools/convert_key_data.py
tools/convert_keycounts.py
tools/process_avogadro_data.py
