Metadata-Version: 2.0
Name: numenta-rogue
Version: 1.0.1
Summary: Metric collection agent for Numenta Rogue showcase application
Home-page: https://github.com/numenta/nupic.rogue
Author: Austin Marshall
Author-email: amarshall@numenta.com
License: UNKNOWN
Keywords: grok,numenta,anomaly detection,monitoring,nupic
Platform: UNKNOWN
Classifier: Environment :: Console
Classifier: Intended Audience :: Developers
Classifier: Intended Audience :: Information Technology
Classifier: License :: OSI Approved :: GNU General Public License (GPL)
Classifier: Programming Language :: Python :: 2
Classifier: Topic :: Utilities
Requires-Dist: gevent
Requires-Dist: psutil
Requires-Dist: grokcli
Provides-Extra: docs
Requires-Dist: sphinx; extra == 'docs'
